setup.py
py_nestle1904.egg-info/PKG-INFO
py_nestle1904.egg-info/SOURCES.txt
py_nestle1904.egg-info/dependency_links.txt
py_nestle1904.egg-info/top_level.txt
pynestle1904/__init__.py
pynestle1904/nestle1904.csv