Metadata-Version: 1.0
Name: py-nestle1904
Version: 0.1
Summary: pip-installable Nestle 1904 with Python API
Home-page: https://github.com/biblicalhumanities/py-nestle1904
Author: James Tauber
Author-email: jtauber@jtauber.com
License: MIT
Platform: UNKNOWN
